README.rst
setup.cfg
setup.py
auto_pack/__init__.py
auto_pack/aliyun_oss_helper.py
auto_pack/autopack.py
auto_pack/checker.py
auto_pack/pack_config.py
auto_pack/pack_producer_config.py
auto_pack/producer.py
auto_pack/sample.py
auto_pack.egg-info/PKG-INFO
auto_pack.egg-info/SOURCES.txt
auto_pack.egg-info/dependency_links.txt
auto_pack.egg-info/requires.txt
auto_pack.egg-info/top_level.txt
auto_pack.egg-info/zip-safe