Metadata-Version: 1.1
Name: auto-pack
Version: 1.3.2
Summary: qudian Android auto pack utils
Home-page: http://www.qudian.com
Author: meng
Author-email: mwping1324@163.com
License: MIT
Keywords: android,Android,auto_pack
Platform: any
Classifier: License :: OSI Approved :: MIT License
Classifier: Programming Language :: Python
Classifier: Intended Audience :: Developers
Classifier: Operating System :: OS Independent
